{
    "language_name": "日本語",
    "language_code": "ja",
    "translations": {
      "NO_FALL_TEXT": "落下ダメージ無効",
      "ENABLED_TEXT": "有効",
      "NOCLIP_TEXT": "ノークリップ",
      "SPEED_TEXT": "移動速度",
      "GODMODE_TEXT": "無敵モード",
      "GODMODE_HINT_TEXT": "主にVer1.0マップで動作します。何かが機能しない場合は無効にしてください。",
      "MULTIHIT_TEXT": "マルチヒット",
      "HIT_COUNT_TEXT": "ヒット数",
      "NO_COOLDOWN_TEXT": "クールダウンなし",
      "FORCE_CRITICAL_TEXT": "強制クリティカル",
      "INFINITE_STAMINA_TEXT": "スタミナ無限",
      "INFINITE_FORTE_TEXT": "フォルテ無限",
      "INFINITE_ULTIMATE_ENERGY_TEXT": "究極スキルエネルギー無限",
      "INFINITE_CONCERTO_ENERGY_TEXT": "協奏エネルギー無限",
      "MAX_RESONANCE_CHAIN_TEXT": "共鳴チェーン最大",
      "FOOD_BUFFS_TEXT": "料理バフ",
      "SHELL_CREDITS_TEXT": "シェル貨+50%",
      "ECHO_DROP_RATE_TEXT": "エコードロップ率+50%",
      "MATERIAL_DROPS_TEXT": "素材ドロップ+50%",
      "PLAYER_BUFFS_TEXT": "プレイヤーバフ",
      "APPLY_TEXT": "適用",
      "BUFF_AMOUNT_TEXT": "バフ量",
      "SPIDER_TEXT": "スパイダーモード",
      "SPIDER_HINT_TEXT": "壁をアニメーションなしで登れます（最大89度）。ただし、空に飛ばされることがあります。",
      "ENTER_RESTRICTED_AREAS_TEXT": "制限エリア侵入",
      "SPEEDHACK_TEXT": "スピードハック",
      "KILLAURA_TEXT": "キルオーラ",
      "KILLAURA_HINT_TEXT": "任務中はこの機能を使用しないでください。",
      "SAFE_MODE_TEXT": "ほぼ安全モード",
      "RADIUS_TEXT": "範囲",
      "ENTITY_VACUUM_TEXT": "エンティティ吸引",
      "COLLECTIBLE_TEXT": "収集物",
      "MONSTER_TEXT": "モンスター",
      "DISTANCE_TEXT": "距離",
      "DUMB_ENEMIES_TEXT": "敵AI低下",
      "DUMB_ENEMIES_HINT_TEXT": "何かが機能しない場合は無効にしてください。",
      "FORCE_SKIP_BUTTON_TEXT": "スキップボタン強制表示",
      "SKIP_DIALOG_TEXT": "会話スキップ",
      "SKIP_DIALOG_HINT_TEXT": "「設定」タブでホットキーを設定し、会話中に長押ししてください。",
      "AUTO_TALK_TEXT": "自動会話進行",
      "NO_COOKING_ANIMATION_TEXT": "料理アニメーションなし",
      "AUTO_MUTTERFLY_TEXT": "マターフライ自動捕獲",
      "AUTO_DESTROY_TEXT": "自動破壊（オブジェクト）",
      "AUTO_LOOT_TEXT": "自動ルート（アイテム拾い）",
      "TREASURE_TEXT": "宝箱",
      "AUTO_ABSORB_TEXT": "自動吸収（エコー）",
      "INTERACTION_TEXT": "インタラクション",
      "CUSTOM_INTERACTION_RANGE_TEXT": "カスタムインタラクト範囲",
      "RANGE_TEXT": "範囲",
      "ESP_TEXT": "ESP（透視）",
      "NAME_TEXT": "名前",
      "BOXES_TEXT": "ボックス表示",
      "TRACERS_TEXT": "トレーサー表示",
      "FILTER_NAMES_TEXT": "フィルター名",
      "COLORS_TEXT": "色",
      "ANIMALS_TEXT": "動物",
      "MONSTERS_TEXT": "モンスター",
      "COLLECTIBLES_TEXT": "収集物",
      "PUZZLES_TEXT": "パズル",
      "OTHER_TEXT": "その他",
      "FILTERS_TEXT": "フィルター",
      "CHEST_TELEPORT_TEXT": "宝箱テレポート",
      "CHEST_TELEPORT_HINT_TEXT": "「設定」タブでホットキーを設定し、押してください。",
      "NO_CHEST_TIP_TEXT": "宝箱が見つかりません",
      "MAP_TELEPORT_TEXT": "マップテレポート",
      "MAP_TELEPORT_HINT_TEXT": "「設定」タブでホットキーを設定し、マップ上の場所をクリックして押してください。",
      "CUSTOM_TELEPORT_TEXT": "カスタムテレポート",
      "EXPORT_NAME_TEXT": "エクスポート名",
      "EXPORT_LIST_TEXT": "リストをエクスポート",
      "IMPORT_LIST_TEXT": "リストをインポート",
      "ADD_TO_LIST_TEXT": "リストに追加",
      "HEIGHT_OFFSET_TEXT": "高さオフセット",
      "AUTO_TP_TEXT": "自動テレポート",
      "COOLDOWN_TEXT": "クールダウン",
      "RUN_LIST_TEXT": "リスト実行",
      "STOP_LIST_TEXT": "リスト停止",
      "TP_TEXT": "テレポート",
      "SELECT_TEXT": "選択",
      "REMOVE_TEXT": "削除",
      "PEEKING_TEXT": "ピーキング",
      "UID_CHANGER_TEXT": "UID変更",
      "SET_UID_TEXT": "UID設定",
      "PLAYER_SCALE_TEXT": "プレイヤーサイズ変更",
      "SCALE_MULTIPLIER_TEXT": "サイズ倍率",
      "FOV_CHANGER_TEXT": "視野角(FOV)変更",
      "FOV_TEXT": "視野角(FOV)",
      "FPS_UNLOCKER_TEXT": "FPSアンロック",
      "FPS_TEXT": "FPS",
      "SHOW_FPS_TEXT": "FPS表示",
      "UE_CONSOLE_TEXT": "UEコンソール",
      "ENABLE_UE_CONSOLE_TEXT": "UEコンソール有効化",
      "UE_CONSOLE_TIP_TEXT": "「~」キーでコンソールを開きます",
      "FUNNY_TEXT": "お遊び機能",
      "BRICK_INSTANCE_TEXT": "ブリックインスタンス",
      "CRASH_GAME_TEXT": "ゲームクラッシュ",
      "FREEZE_GAME_TEXT": "ゲームフリーズ",
      "FIXES_TEXT": "修正",
      "FIXES_LABEL_TEXT": "何かが壊れた場合のみクリックしてください！",
      "FIX_KILLAURA_TEXT": "キルオーラ修正",
      "FIX_AUTO_DESTROY_TEXT": "自動破壊修正",
      "FIX_INTERACT_RANGE_TEXT": "インタラクト範囲修正",
      "FIX_MAX_RES_CHAIN_TEXT": "共鳴チェーン最大化修正",
      "FIX_ENERGY_BUFFS_TEXT": "エネルギーバフ修正",
      "FIX_FOOD_BUFFS_TEXT": "料理バフ修正",
      "ACCENT_TEXT": "アクセントカラー",
      "TEXT_STATIC_TEXT": "テキスト（静的）",
      "TEXT_ENABLED_TEXT": "テキスト（有効時）",
      "TEXT_DISABLED_TEXT": "テキスト（無効時）",
      "BORDER_TEXT": "境界線",
      "FRAME_INACTIVE_TEXT": "フレーム（非アクティブ）",
      "FRAME_ACTIVE_TEXT": "フレーム（アクティブ）",
      "BUTTON_TEXT": "ボタン",
      "BUTTON_HOVERED_TEXT": "ボタン（ホバー時）",
      "BUTTON_ACTIVE_TEXT": "ボタン（アクティブ時）",
      "GROUP_BOX_BG_TEXT": "グループボックス背景",
      "GROUP_TITLE_TEXT": "グループタイトル",
      "WINDOW_BACKGROUND_TEXT": "ウィンドウ背景",
      "SELECT_THEME_TEXT": "テーマ選択",
      "EXPORT_THEME_TEXT": "テーマをエクスポート",
      "CUSTOM_IMAGE_TEXT": "カスタム画像",
      "LOAD_TEXT": "読み込み",
      "BUFFED_PLAYER_TIP_TEXT": "強化されたプレイヤー",
      "WALK_SPEED_TEXT": "歩行速度",
      "PLAYER_GROUP_TEXT": "プレイヤー",
      "COMBAT_TAB_TEXT": "戦闘",
      "BUFFS_TAB_TEXT": "バフ",
      "MOVEMENT_TAB_TEXT": "移動",
      "WORLD_GROUP_TEXT": "ワールド",
      "EXPLOITS_TAB_TEXT": "便利機能",
      "CUTSCENES_TAB_TEXT": "カットシーン",
      "FARMING_TAB_TEXT": "収集・周回",
      "VISUALS_GROUP_TEXT": "表示",
      "ESP_TAB_TEXT": "ESP",
      "FILTERS_TAB_TEXT": "フィルター",
      "TELEPORT_GROUP_TEXT": "テレポート",
      "DYNAMIC_TP_TAB_TEXT": "ダイナミックTP",
      "CUSTOM_TP_TAB_TEXT": "カスタムTP",
      "OTHER_GROUP_TEXT": "その他",
      "MISCELLANEOUS_TAB_TEXT": "その他いろいろ",
      "SETTINGS_TAB_TEXT": "設定",
      "LANGUAGE_TEXT": "言語",
      "IMAGE_OPACITY_TEXT": "画像不透明度",
      "CREDITS_TEXT": "クレジット",
      "ENTER_LICENSE_TEXT": "ライセンスを入力:",
      "HOTKEYS_TEXT": "ホットキー",
      "HOTKEYS_HINT_TEXT": "これらが機能しない場合、Windowsの実験的ビルドを使用している可能性があります。",
      "SEARCH_TEXT": "検索",
      "DEVELOPER_TEAM_TEXT": "開発チーム",
      "TRANSLATORS_TEXT": "翻訳者",
      "FILTER_CONTRIBUTORS_TEXT": "フィルター貢献者",
      "NEXT_TELEPORT_TEXT": "次のテレポート先",
      "PREVIOUS_TELEPORT_TEXT": "前のテレポート先",
      "TOGGLE_UI_TEXT": "UI表示切替",
      "MENU_TEXT": "メニュー"
    }
}